kgate/__init__.py
kgate/architect.py
kgate/cli.py
kgate/config_template.toml
kgate/decoders/__init__.py
kgate/decoders/bilinear.py
kgate/decoders/convolutional.py
kgate/decoders/translational.py
kgate/encoders.py
kgate/evaluators.py
kgate/grid_search.py
kgate/inference.py
kgate/knowledgegraph.py
kgate/preprocessing.py
kgate/samplers.py
kgate/utils.py
kgate-0.2.20.dist-info/LICENSE
kgate-0.2.20.dist-info/METADATA
kgate-0.2.20.dist-info/WHEEL
kgate-0.2.20.dist-info/RECORD
