Metadata-Version: 2.3
Name: KGATE
Version: 0.2.20
Summary: Knowledge Graph Autoencoder Training Environment, bridging PyG encoders and TorchKGE decoders.
License: MIT
Keywords: Knowledge Graph,Knowledge Graph Embedding,Autoencoder,Machine Learning,Link Prediction
Author: Benjamin Loire
Author-email: benjamin.loire@univ-amu.fr
Requires-Python: >=3.10
Classifier: Development Status :: 3 - Alpha
Classifier: Intended Audience :: Science/Research
Classifier: Topic :: Scientific/Engineering :: Artificial Intelligence
Requires-Dist: matplotlib (>=3.10.0,<4.0.0)
Requires-Dist: optuna (>=4.2.1,<5.0.0)
Requires-Dist: pytest (>=8.3.4,<9.0.0)
Requires-Dist: pytorch-ignite (>=0.5.1,<0.6.0)
Requires-Dist: pyyaml (>=6.0.2,<7.0.0)
Requires-Dist: tomli-w (>=1.2.0,<2.0.0)
Requires-Dist: torch-geometric (>=2.6.1,<3.0.0)
Requires-Dist: torchkge (>=0.17.7,<0.18.0)
Project-URL: Repository, https://github.com/BAUDOTlab/KGATE
Project-URL: issues, https://github.com/BAUDOTlab/KGATE/issues
